ssbio/__init__.py
ssbio/utils.py
ssbio/biopython/__init__.py
ssbio/biopython/bp_mmcif2dict.py
ssbio/biopython/bp_mmcifparser.py
ssbio/core/__init__.py
ssbio/core/complex.py
ssbio/core/genepro.py
ssbio/core/modelpro.py
ssbio/core/object.py
ssbio/core/protein.py
ssbio/databases/__init__.py
ssbio/databases/bigg.py
ssbio/databases/hmmer.py
ssbio/databases/kegg.py
ssbio/databases/ncbi.py
ssbio/databases/patric.py
ssbio/databases/pdb.py
ssbio/databases/pisa.py
ssbio/databases/swissmodel.py
ssbio/databases/uniprot.py
ssbio/io/__init__.py
ssbio/io/validation.py
ssbio/pipeline/__init__.py
ssbio/pipeline/atlas.py
ssbio/pipeline/gempro.py
ssbio/protein/__init__.py
ssbio/protein/sequence/__init__.py
ssbio/protein/sequence/seqprop.py
ssbio/protein/sequence/properties/__init__.py
ssbio/protein/sequence/properties/aggregation_propensity.py
ssbio/protein/sequence/properties/kinetic_folding_rate.py
ssbio/protein/sequence/properties/residues.py
ssbio/protein/sequence/properties/scratch.py
ssbio/protein/sequence/properties/thermostability.py
ssbio/protein/sequence/properties/tmhmm.py
ssbio/protein/sequence/utils/__init__.py
ssbio/protein/sequence/utils/alignment.py
ssbio/protein/sequence/utils/blast.py
ssbio/protein/sequence/utils/fasta.py
ssbio/protein/sequence/utils/utils.py
ssbio/protein/structure/__init__.py
ssbio/protein/structure/chainprop.py
ssbio/protein/structure/structprop.py
ssbio/protein/structure/homology/__init__.py
ssbio/protein/structure/homology/itasser/__init__.py
ssbio/protein/structure/homology/itasser/itasserprep.py
ssbio/protein/structure/homology/itasser/itasserprop.py
ssbio/protein/structure/properties/__init__.py
ssbio/protein/structure/properties/dssp.py
ssbio/protein/structure/properties/fatcat.py
ssbio/protein/structure/properties/freesasa.py
ssbio/protein/structure/properties/msms.py
ssbio/protein/structure/properties/opm.py
ssbio/protein/structure/properties/quality.py
ssbio_edbr-0.9.9.7.dist-info/METADATA
ssbio_edbr-0.9.9.7.dist-info/RECORD
ssbio_edbr-0.9.9.7.dist-info/WHEEL
ssbio_edbr-0.9.9.7.dist-info/top_level.txt
