Metadata-Version: 2.1
Name: ssbio-edbr
Version: 0.9.9.7
Summary: Tools to enable structural systems biology, forked from SBRG/ssbio
Home-page: http://github.com/i386uk/ssbio
Author: Xiaofan Li
Author-email: xli@edbr.uk
License: MIT
Download-URL: https://github.com/i386uk/ssbio/archive/v0.9.9.7.tar.gz
Platform: UNKNOWN
Requires-Dist: numpy
Requires-Dist: pandas
Requires-Dist: tqdm
Requires-Dist: six
Requires-Dist: requests (>=2.13.0)
Requires-Dist: cobra (>=0.6.1)
Requires-Dist: biopython (>=1.69)
Requires-Dist: bioservices
Requires-Dist: xmltodict
Requires-Dist: mmtf-python
Requires-Dist: msgpack-python
Requires-Dist: awesome-slugify
Requires-Dist: ipywidgets (==7.0.0)
Requires-Dist: lxml
Requires-Dist: json-tricks (>3.0)
Requires-Dist: seaborn
Requires-Dist: matplotlib
Requires-Dist: beautifulsoup4 (==4.5.3)
Requires-Dist: nbsphinx
Requires-Dist: bcbio-gff
Requires-Dist: biopandas
Requires-Dist: more-itertools
Requires-Dist: slugify
Requires-Dist: bcbio-gff
Requires-Dist: scipy
Requires-Dist: pytest
Requires-Dist: deprecation
